aggmap/AggMapNet.py
aggmap/__init__.py
aggmap/_devmap.py
aggmap/map.py
aggmap/show.py
aggmap/aggmodel/__init__.py
aggmap/aggmodel/cbks.py
aggmap/aggmodel/explain_dev.py
aggmap/aggmodel/explainer.py
aggmap/aggmodel/loss.py
aggmap/aggmodel/net.py
aggmap/utils/__init__.py
aggmap/utils/calculator.py
aggmap/utils/distances.py
aggmap/utils/gen_nwk.py
aggmap/utils/logtools.py
aggmap/utils/matrixopt.py
aggmap/utils/multiproc.py
aggmap/utils/summary.py
aggmap/utils/vismap.py
aggmap-1.2.1.dist-info/LICENSE
aggmap-1.2.1.dist-info/METADATA
aggmap-1.2.1.dist-info/WHEEL
aggmap-1.2.1.dist-info/top_level.txt
aggmap-1.2.1.dist-info/RECORD
