Metadata-Version: 2.1
Name: aggmap
Version: 1.2.1
Summary: Jigsaw-like AggMap: A Robust and Explainable Omics Deep Learning Tool
Home-page: https://github.com/shenwanxiang/bidd-aggmap/tree/master
Author: WanXiang Shen
License-File: LICENSE
Requires-Dist: shap ==0.42.1
Requires-Dist: pandas ==1.1.5
Requires-Dist: seaborn ==0.9.1
Requires-Dist: numba ==0.58.0
Requires-Dist: scikit-learn ==1.2.2
Requires-Dist: joblib ==1.3.2
Requires-Dist: scipy
Requires-Dist: umap-learn ==0.3.9
Requires-Dist: python-highcharts ==0.4.2
Requires-Dist: tqdm
Requires-Dist: colored
Requires-Dist: colorlog ==4.0.2
Requires-Dist: lapjv
Requires-Dist: numpy ==1.24.4
Requires-Dist: tensorflow-gpu ==2.9.1
Provides-Extra: dev
Requires-Dist: pytest ; extra == 'dev'
